aws/__init__.py
aws/client.py
aws/paginate.py
aws/reference.py
aws/session.py
aws/vpc.py
torvo_aws-1.0.1652836907.dist-info/LICENSE
torvo_aws-1.0.1652836907.dist-info/METADATA
torvo_aws-1.0.1652836907.dist-info/WHEEL
torvo_aws-1.0.1652836907.dist-info/top_level.txt
torvo_aws-1.0.1652836907.dist-info/RECORD
