Metadata-Version: 2.1
Name: torvo-aws
Version: 1.0.1652836907
Summary: AWS infrastructure as code
Home-page: https://torvo.com.au
Author: Torvo
Author-email: ben@torvo.com.au
Project-URL: Documentation, https://torvo.com.au/python3/torvo-aws/index.html
Classifier: Programming Language :: Python :: 3
Classifier: License :: OSI Approved :: Apache Software License
Classifier: Operating System :: OS Independent
Requires-Python: >=3.6
License-File: LICENSE
Requires-Dist: boto3
